co3/__init__.py
resilient/LICENSE
resilient/__init__.py
resilient/app_config.py
resilient/co3.py
resilient/co3argparse.py
resilient/co3base.py
resilient/co3sslutil.py
resilient/constants.py
resilient/definitions.py
resilient/helpers.py
resilient/patch.py
resilient/resilient_rest_mock.py
resilient/bin/__init__.py
resilient/bin/finfo.py
resilient/bin/gadget.py
resilient/bin/res_keyring.py
resilient-51.0.7.2.16540.dist-info/METADATA
resilient-51.0.7.2.16540.dist-info/WHEEL
resilient-51.0.7.2.16540.dist-info/entry_points.txt
resilient-51.0.7.2.16540.dist-info/top_level.txt
resilient-51.0.7.2.16540.dist-info/RECORD
