Metadata-Version: 2.4
Name: resilient
Version: 51.0.7.2.16540
Summary: Python client module for the IBM SOAR REST API
Home-page: https://github.com/ibmresilient/resilient-python-api/tree/main/resilient
Author: IBM SOAR
License: MIT
Project-URL: Documentation, https://ibm.biz/soar-docs
Project-URL: API Docs, https://ibm.biz/soar-python-docs
Project-URL: IBM Community, https://ibm.biz/soarcommunity
Project-URL: Change Log, https://ibm.biz/resilient-changes
Keywords: ibm,soar,resilient,resilient-circuits,circuits,resilient-sdk,sdk
Classifier: Programming Language :: Python :: 3.9
Classifier: Programming Language :: Python :: 3.11
Classifier: Programming Language :: Python :: 3.12
Requires-Python: >=3.9
Requires-Dist: resilient-app-config-plugins
Requires-Dist: retry2~=0.9
Requires-Dist: requests-toolbelt~=1.0
Requires-Dist: six~=1.16
Requires-Dist: keyring~=23.5
Requires-Dist: cachetools~=5.0
Requires-Dist: setuptools~=79.0
Requires-Dist: jwcrypto~=1.5.6
Requires-Dist: requests~=2.32
